{
  "name": "@webpack-cli/serve",
  "description": "[![npm downloads][downloads]][downloads-url]",
  "keywords": [],
  "license": "mit",
  "homepage": "https://github.com/webpack/webpack-cli/tree/master/packages/serve",
  "repository": {
    "type": "git",
    "url": "git+https://github.com/webpack/webpack-cli.git"
  },
  "version": "2.0.5",
  "peerDependencies": {
    "webpack": "5.x.x",
    "webpack-cli": "5.x.x"
  },
  "users": [],
  "readme": "",
  "dependencies": {},
  "devDependencies": {},
  "developers": [
    "evenstensberg@gmail.com",
    "my.burning@gmail.com",
    "sheo13666q@gmail.com"
  ],
  "kwds": "[![npm downloads][downloads]][downloads-url]",
  "license_kwds": "mit",
  "libtype": "npm",
  "id": "npm__webpack_cli_serve",
  "dependency_ids": [
    "npm_webpack",
    "npm_webpack_cli"
  ]
}