{
  "name": "engine.io-parser",
  "description": "parser for the client for the realtime engine",
  "license": "mit",
  "homepage": "https://github.com/socketio/engine.io-parser",
  "repository": {
    "type": "git",
    "url": "git+ssh://git@github.com/socketio/engine.io-parser.git"
  },
  "version": "5.2.1",
  "devDependencies": {
    "@babel/core": "~7.9.6",
    "@babel/preset-env": "~7.9.6",
    "@types/mocha": "^9.0.0",
    "@types/node": "^16.9.6",
    "babelify": "^10.0.0",
    "benchmark": "^2.1.4",
    "expect.js": "0.3.1",
    "mocha": "^5.2.0",
    "nyc": "~15.0.1",
    "prettier": "^1.19.1",
    "rimraf": "^3.0.2",
    "socket.io-browsers": "^1.0.4",
    "ts-node": "^10.2.1",
    "tsify": "^5.0.4",
    "typescript": "^4.4.3",
    "zuul": "3.11.1",
    "zuul-ngrok": "4.0.0"
  },
  "keywords": [],
  "users": [],
  "readme": "",
  "dependencies": {},
  "peerDependencies": {},
  "developers": [
    "damien.arrachequesne@gmail.com",
    "rauchg@gmail.com"
  ],
  "kwds": "parser for the client for the realtime engine",
  "license_kwds": "mit",
  "libtype": "npm",
  "id": "npm_engine.io_parser",
  "dependency_ids": [
    "npm__babel_core",
    "npm__babel_preset_env",
    "npm__types_mocha",
    "npm__types_node",
    "npm_babelify",
    "npm_benchmark",
    "npm_expect.js",
    "npm_mocha",
    "npm_nyc",
    "npm_prettier",
    "npm_rimraf",
    "npm_socket.io_browsers",
    "npm_ts_node",
    "npm_tsify",
    "npm_typescript",
    "npm_zuul",
    "npm_zuul_ngrok"
  ]
}