{
  "name": "github-basic",
  "description": "basic https interface to github",
  "keywords": [],
  "license": "mit",
  "homepage": "https://github.com/forbeslindesay/github-basic#readme",
  "repository": {
    "type": "git",
    "url": "git+https://github.com/ForbesLindesay/github-basic.git"
  },
  "version": "6.0.0",
  "dependencies": {
    "barrage": "^1.1.0",
    "is-browser": "^2.0.1",
    "parse-links": "0.1.0",
    "promise": "^7.0.1",
    "sync-request": "^3.0.0",
    "then-request": "^2.1.1"
  },
  "devDependencies": {
    "mocha": "*"
  },
  "users": [],
  "readme": "",
  "peerDependencies": {},
  "developers": [
    "forbes@lindesay.co.uk",
    "forbeslindesay"
  ],
  "kwds": "basic https interface to github",
  "license_kwds": "mit",
  "libtype": "npm",
  "id": "npm_github_basic",
  "dependency_ids": [
    "npm_barrage",
    "npm_is_browser",
    "npm_mocha",
    "npm_parse_links",
    "npm_promise",
    "npm_sync_request",
    "npm_then_request"
  ]
}