{
  "name": "lsr",
  "description": "recursive readdir (`ls -r`)",
  "keywords": [],
  "license": "mit",
  "homepage": "https://github.com/forbeslindesay/lsr#readme",
  "repository": {
    "type": "git",
    "url": "git+https://github.com/ForbesLindesay/lsr.git"
  },
  "version": "2.0.0",
  "dependencies": {
    "@types/node": "^7.0.31",
    "barrage": "^1.1.0",
    "promise": "^7.2.0"
  },
  "devDependencies": {
    "mocha": "*",
    "typescript": "^2.3.4"
  },
  "users": [],
  "readme": "",
  "peerDependencies": {},
  "developers": [
    "forbes@lindesay.co.uk",
    "forbeslindesay"
  ],
  "kwds": "recursive readdir (`ls -r`)",
  "license_kwds": "mit",
  "libtype": "npm",
  "id": "npm_lsr",
  "dependency_ids": [
    "npm__types_node",
    "npm_barrage",
    "npm_mocha",
    "npm_promise",
    "npm_typescript"
  ]
}