{
  "name": "weakmap-polyfill",
  "description": "ecmascript6 weakmap polyfill",
  "keywords": [
    "ecmascript",
    "es2015",
    "es6",
    "javascript",
    "polyfill",
    "shim",
    "weakmap"
  ],
  "license": "mit",
  "homepage": "https://github.com/polygonplanet/weakmap-polyfill",
  "repository": {
    "type": "git",
    "url": "git+https://github.com/polygonplanet/weakmap-polyfill.git"
  },
  "version": "2.0.4",
  "dependencies": {},
  "devDependencies": {
    "es5-shim": "^4.5.15",
    "eslint": "^7.28.0",
    "karma": "^6.3.3",
    "karma-chrome-launcher": "^3.1.0",
    "karma-detect-browsers": "^2.3.3",
    "karma-firefox-launcher": "^2.1.1",
    "karma-ie-launcher": "^1.0.0",
    "karma-mocha": "^2.0.1",
    "karma-mocha-reporter": "^2.2.5",
    "karma-safari-launcher": "^1.0.0",
    "mocha": "^8.4.0",
    "power-assert": "^1.6.1",
    "uglify-js": "^3.13.9"
  },
  "users": [],
  "readme": "",
  "peerDependencies": {},
  "developers": [
    "polygon.planet.aqua@gmail.com"
  ],
  "kwds": "ecmascript6 weakmap polyfill ecmascript es2015 es6 javascript polyfill shim weakmap",
  "license_kwds": "mit",
  "libtype": "npm",
  "id": "npm_weakmap_polyfill",
  "dependency_ids": [
    "npm_es5_shim",
    "npm_eslint",
    "npm_karma",
    "npm_karma_chrome_launcher",
    "npm_karma_detect_browsers",
    "npm_karma_firefox_launcher",
    "npm_karma_ie_launcher",
    "npm_karma_mocha",
    "npm_karma_mocha_reporter",
    "npm_karma_safari_launcher",
    "npm_mocha",
    "npm_power_assert",
    "npm_uglify_js"
  ]
}