{
  "classifiers": [
    "development status :: 4 - beta",
    "environment :: web environment",
    "framework :: django",
    "intended audience :: developers",
    "license :: osi approved :: bsd license",
    "operating system :: os independent",
    "programming language :: python",
    "programming language :: python :: 2",
    "programming language :: python :: 3",
    "topic :: utilities"
  ],
  "description": "===============\ndjango-tastypie\n===============\n\n.. image:: https://readthedocs.org/projects/django-tastypie/badge/\n    :target: https://django-tastypie.readthedocs.io/\n    :alt: docs\n\n.. image:: https://github.com/django-tastypie/django-tastypie/actions/workflows/python-package.yml/badge.svg\n    :target: https://github.com/django-tastypie/django-tastypie/actions\n    :alt: ci\n\n.. image:: https://coveralls.io/repos/django-tastypie/django-tastypie/badge.svg?service=github\n    :target: https://coveralls.io/github/django-tastypie/django-tastypie\n    :alt: code coverage\n\n.. image:: https://img.shields.io/pypi/v/django-tastypie.svg\n    :target: https://pypi.python.org/pypi/django-tastypie\n    :alt: version\n\n.. image:: https://pypi-badges.global.ssl.fastly.net/svg?package=django-tastypie&timeframe=monthly\n    :target: https://pypi.python.org/pypi/django-tastypie\n    :alt: downloads\n\ncreating delicious apis for django apps since 2010.\n\ncurrently in beta but being used actively in production on several\nsites.\n\n\nrequirements\n============\n\ncore\n----\n\n* python 3.6+, preferably 3.8+ (whatever is supported by your version of django)\n* django 4.2, 3.2 (lts releases), or django 4.0 / 4.1 (intermediate releases)\n* dateutil (http://labix.org/python-dateutil) >= 2.1\n\nformat support\n--------------\n\n* xml: lxml 3 (http://lxml.de/) and defusedxml (https://pypi.python.org/pypi/defusedxml)\n* yaml: pyyaml (http://pyyaml.org/)\n* binary plist: biplist (https://bitbucket.org/wooster/biplist)\n\noptional\n--------\n\n* http digest authentication: python3-digest (https://bitbucket.org/akoha/python-digest/)\n\n\nwhat's it look like?\n====================\n\na basic example looks like:\n\n.. code:: python\n\n    # myapp/api.py\n    # ============\n    from tastypie.resources import modelresource\n    from myapp.models import entry\n\n\n    class entryresource(modelresource):\n        class meta:\n            queryset = entry.objects.all()\n\n\n    # urls.py\n    # =======\n    from django.urls.conf import re_path, include\n    from tastypie.api import api\n    from myapp.api import entryresource\n\n    v1_api = api(api_name='v1')\n    v1_api.register(entryresource())\n\n    urlpatterns = [\n        # the normal jazz here then...\n        re_path(r'^api/', include(v1_api.urls)),\n    ]\n\nthat gets you a fully working, read-write api for the ``entry`` model that\nsupports all crud operations in a restful way. json/xml/yaml support is already\nthere, and it's easy to add related data/authentication/caching.\n\nyou can find more in the documentation at\nhttps://django-tastypie.readthedocs.io/.\n\n\nwhy tastypie?\n=============\n\nthere are other api frameworks out there for django. you need to\nassess the options available and decide for yourself. that said, here are some\ncommon reasons for tastypie.\n\n* you need an api that is restful and uses http well.\n* you want to support deep relations.\n* you don't want to have to write your own serializer to make the output right.\n* you want an api framework that has little magic, very flexible and maps well to\n  the problem domain.\n* you want/need xml serialization that is treated equally to json (and yaml is\n  there too).\n\n\nreference material\n==================\n\n* https://django-tastypie.readthedocs.io/en/latest/\n* https://github.com/django-tastypie/django-tastypie/tree/master/tests/basic shows\n  basic usage of tastypie\n* http://en.wikipedia.org/wiki/rest\n* http://en.wikipedia.org/wiki/list_of_http_status_codes\n* http://www.ietf.org/rfc/rfc2616.txt\n* http://jacobian.org/writing/rest-worst-practices/\n\n\ngetting help\n============\n\nthere are two primary ways of getting help.\n\n1. go to `stackoverflow`_ and post a question with the ``tastypie`` tag.\n2. we have an irc channel (`#tastypie on irc.freenode.net`_) to get help,\n   bounce an idea by us, or generally shoot the breeze.\n\n.. _`stackoverflow`: https://stackoverflow.com/questions/tagged/tastypie\n.. _#tastypie on irc.freenode.net: irc://irc.freenode.net/tastypie\n\n\nsecurity\n========\n\ntastypie is committed to providing a flexible and secure api, and was designed\nwith many security features and options in mind. due to the complex nature of\napis and the constant discovery of new attack vectors and vulnerabilities,\nno software is immune to security holes. we rely on our community to report\nand help us investigate security issues.\n\nif you come across a security hole **please do not open a github issue**.\ninstead, **drop us an email** at ``tastypie-security@googlegroups.com``\n\nwe'll then work together to investigate and resolve the problem so we can\nannounce a solution along with the vulnerability.\n\n\n",
  "docs_url": null,
  "keywords": "",
  "license": "",
  "name": "django-tastypie",
  "package_url": "https://pypi.org/project/django-tastypie/",
  "project_url": "https://pypi.org/project/django-tastypie/",
  "project_urls": {
    "Homepage": "https://github.com/django-tastypie/django-tastypie"
  },
  "release_url": "https://pypi.org/project/django-tastypie/0.14.6/",
  "requires_dist": [],
  "requires_python": "",
  "summary": "a flexible & capable api layer for django.",
  "version": "0.14.6",
  "releases": [],
  "developers": [
    "daniel@toastdriven.com",
    "daniel_lindsley"
  ],
  "kwds": "django tastypie badge badges yaml",
  "license_kwds": "",
  "libtype": "pypi",
  "id": "pypi_django_tastypie",
  "homepage": "https://github.com/django-tastypie/django-tastypie",
  "release_count": 27,
  "dependency_ids": []
}