{
  "classifiers": [
    "development status :: 5 - production/stable",
    "environment :: console",
    "intended audience :: developers",
    "intended audience :: science/research",
    "license :: osi approved :: mit license",
    "programming language :: python",
    "programming language :: python :: 2.7",
    "programming language :: python :: 3.4",
    "topic :: text processing"
  ],
  "description": "maintained fork of pdfminer using six for python 2+3 compatibility\n\npdfminer is a tool for extracting information from pdf documents.\nunlike other pdf-related tools, it focuses entirely on getting\nand analyzing text data. pdfminer allows to obtain\nthe exact location of texts in a page, as well as\nother information such as fonts or lines.\nit includes a pdf converter that can transform pdf files\ninto other text formats (such as html). it has an extensible\npdf parser that can be used for other purposes instead of text analysis.",
  "docs_url": null,
  "keywords": "pdf parser,pdf converter,layout analysis,text mining",
  "license": "mit",
  "name": "pdfminer2",
  "package_url": "https://pypi.org/project/pdfminer2/",
  "project_url": "https://pypi.org/project/pdfminer2/",
  "project_urls": {
    "Download": "UNKNOWN",
    "Homepage": "https://github.com/metachris/pdfminer"
  },
  "release_url": "https://pypi.org/project/pdfminer2/20151206/",
  "requires_dist": [],
  "requires_python": null,
  "summary": "pdf parser and analyzer",
  "version": "20151206",
  "releases": [],
  "developers": [
    "chris@linuxuser.at",
    "chris_hager"
  ],
  "kwds": "pdfminer pdf analyzer python parser",
  "license_kwds": "mit",
  "libtype": "pypi",
  "id": "pypi_pdfminer2",
  "homepage": "https://github.com/metachris/pdfminer",
  "release_count": 1,
  "dependency_ids": []
}