{
  "classifiers": [
    "programming language :: python",
    "programming language :: python :: 2",
    "programming language :: python :: 3",
    "topic :: software development",
    "topic :: software development :: libraries",
    "topic :: software development :: libraries :: python modules"
  ],
  "description": "unknown\n\n\n",
  "docs_url": null,
  "keywords": "",
  "license": "mit",
  "name": "pypd",
  "package_url": "https://pypi.org/project/pypd/",
  "project_url": "https://pypi.org/project/pypd/",
  "project_urls": {
    "Download": "https://github.com/PagerDuty/pagerduty-api-python-client/archive/master.tar.gz",
    "Homepage": "https://github.com/PagerDuty/pagerduty-api-python-client"
  },
  "release_url": "https://pypi.org/project/pypd/1.1.0/",
  "requires_dist": [
    "requests",
    "six"
  ],
  "requires_python": "",
  "summary": "a python client for pagerduty api",
  "version": "1.1.0",
  "releases": [],
  "developers": [
    "abrooks@pagerduty.com",
    "jd_cumpson"
  ],
  "kwds": "unknown a python client for pagerduty api",
  "license_kwds": "mit",
  "libtype": "pypi",
  "id": "pypi_pypd",
  "homepage": "https://github.com/pagerduty/pagerduty-api-python-client",
  "release_count": 3,
  "dependency_ids": [
    "pypi_requests",
    "pypi_six"
  ]
}