{
  "classifiers": [
    "license :: osi approved :: apache software license",
    "programming language :: python :: 3",
    "typing :: stubs only"
  ],
  "description": "## typing stubs for cachetools\n\nthis is a [pep 561](https://peps.python.org/pep-0561/)\ntype stub package for the [`cachetools`](https://github.com/tkem/cachetools) package.\nit can be used by type-checking tools like\n[mypy](https://github.com/python/mypy/),\n[pyright](https://github.com/microsoft/pyright),\n[pytype](https://github.com/google/pytype/),\npycharm, etc. to check code that uses\n`cachetools`.\n\nthis version of `types-cachetools` aims to provide accurate annotations\nfor `cachetools==5.3.*`.\nthe source for this package can be found at\nhttps://github.com/python/typeshed/tree/main/stubs/cachetools. all fixes for\ntypes and metadata should be contributed there.\n\nsee https://github.com/python/typeshed/blob/main/readme.md for more details.\nthis package was generated from typeshed commit `1c184fea33d50ba430410cf1b25d4aea2df2981e` and was tested\nwith mypy 1.6.1, pyright 1.1.332, and\npytype 2023.10.17.\n",
  "docs_url": null,
  "keywords": "",
  "license": "apache-2.0 license",
  "name": "types-cachetools",
  "package_url": "https://pypi.org/project/types-cachetools/",
  "project_url": "https://pypi.org/project/types-cachetools/",
  "project_urls": {
    "Changes": "https://github.com/typeshed-internal/stub_uploader/blob/main/data/changelogs/cachetools.md",
    "Chat": "https://gitter.im/python/typing",
    "GitHub": "https://github.com/python/typeshed",
    "Homepage": "https://github.com/python/typeshed",
    "Issue tracker": "https://github.com/python/typeshed/issues"
  },
  "release_url": "https://pypi.org/project/types-cachetools/5.3.0.7/",
  "requires_dist": [],
  "requires_python": ">=3.7",
  "summary": "typing stubs for cachetools",
  "version": "5.3.0.7",
  "releases": [],
  "developers": [],
  "kwds": "cachetools pycharm python pytype types",
  "license_kwds": "apache-2.0 license",
  "libtype": "pypi",
  "id": "pypi_types_cachetools",
  "homepage": "https://github.com/python/typeshed",
  "release_count": 35,
  "dependency_ids": []
}